MANIFEST.in
README.rst
bootstrap.py
buildout.cfg
setup.py
antispoofing/__init__.py
antispoofing.verification.gmm.egg-info/PKG-INFO
antispoofing.verification.gmm.egg-info/SOURCES.txt
antispoofing.verification.gmm.egg-info/dependency_links.txt
antispoofing.verification.gmm.egg-info/entry_points.txt
antispoofing.verification.gmm.egg-info/namespace_packages.txt
antispoofing.verification.gmm.egg-info/requires.txt
antispoofing.verification.gmm.egg-info/top_level.txt
antispoofing.verification.gmm.egg-info/zip-safe
antispoofing/verification/__init__.py
antispoofing/verification/faceloc/__init__.py
antispoofing/verification/faceloc/anthropometry.py
antispoofing/verification/features/__init__.py
antispoofing/verification/features/dct.py
antispoofing/verification/gmm/__init__.py
antispoofing/verification/gmm/version.py
antispoofing/verification/gmm/config/__init__.py
antispoofing/verification/gmm/config/gmm_replay.py
antispoofing/verification/gmm/script/__init__.py
antispoofing/verification/gmm/script/build_score_files.py
antispoofing/verification/gmm/script/enrol.py
antispoofing/verification/gmm/script/feature_extract.py
antispoofing/verification/gmm/script/generate_statistics.py
antispoofing/verification/gmm/script/plot_scores.py
antispoofing/verification/gmm/script/plot_scores_and_counterm.py
antispoofing/verification/gmm/script/score.py
antispoofing/verification/gmm/script/show_culprit.py
antispoofing/verification/gmm/script/train_ubm.py
antispoofing/verification/utils/__init__.py