Metadata-Version: 1.0
Name: antispoofing.verification.gmm
Version: 1.0.2
Summary: Replay-Attack Face Verification Package Based on a Parts-Based Gaussian Mixture Models
Home-page: http://pypi.python.org/pypi/antispoofing.verification.gmm
Author: Andre Anjos
Author-email: andre.anjos@idiap.ch
License: GPLv3
Platform: UNKNOWN
